azdo_harvest/__init__.py
azdo_harvest/cli.py
azdo_harvest/downloader.py
azdo_harvest/models.py
azdo_harvest/search.py
azdo_harvest-0.2.0.dist-info/METADATA
azdo_harvest-0.2.0.dist-info/WHEEL
azdo_harvest-0.2.0.dist-info/entry_points.txt
azdo_harvest-0.2.0.dist-info/licenses/LICENSE
azdo_harvest-0.2.0.dist-info/RECORD
