Metadata-Version: 2.4
Name: azdo-harvest
Version: 0.2.0
Summary: Search and collect files across Azure Devops Organizations
License: MIT
License-File: LICENSE
Keywords: azure,devops,search,api,cli,azure-devops,repository-search
Author: rothoma2
Author-email: thomcrnl@gmail.com
Requires-Python: >=3.10
Classifier: Development Status :: 4 - Beta
Classifier: Intended Audience :: Developers
Classifier: License :: OSI Approved :: MIT License
Classifier: Programming Language :: Python :: 3
Classifier: Programming Language :: Python :: 3.10
Classifier: Operating System :: OS Independent
Classifier: Topic :: Software Development :: Libraries :: Python Modules
Classifier: Topic :: Utilities
Provides-Extra: dev
Requires-Dist: click (>=8.1.0)
Requires-Dist: pytest (>=7.0.0) ; extra == "dev"
Requires-Dist: pytest-cov (>=4.0.0) ; extra == "dev"
Requires-Dist: requests (>=2.31.0)
Requires-Dist: rich (>=13.0.0)
Project-URL: Documentation, https://github.com/rothoma2/azdo-harvest#readme
Project-URL: Homepage, https://github.com/rothoma2/azdo-harvest
Project-URL: Issues, https://github.com/rothoma2/azdo-harvest/issues
Project-URL: Repository, https://github.com/rothoma2/azdo-harvest
